phl_budget_data/__init__.py
phl_budget_data/cli/__init__.py
phl_budget_data/cli/__main__.py
phl_budget_data/cli/etl.py
phl_budget_data/cli/scrape.py
phl_budget_data/data/historical/qcmr/cash-reports-fund-balances.csv
phl_budget_data/data/historical/qcmr/cash-reports-net-cash-flow.csv
phl_budget_data/data/historical/qcmr/cash-reports-revenue.csv
phl_budget_data/data/historical/qcmr/cash-reports-spending.csv
phl_budget_data/data/historical/qcmr/department-obligations.csv
phl_budget_data/data/historical/qcmr/fulltime-positions.csv
phl_budget_data/data/historical/qcmr/personal-services-summary.csv
phl_budget_data/data/historical/revenue/birt-collections-by-sector.csv
phl_budget_data/data/historical/revenue/city-collections.csv
phl_budget_data/data/historical/revenue/city-tax-collections.csv
phl_budget_data/data/historical/revenue/sales-collections-by-sector.csv
phl_budget_data/data/historical/revenue/school-collections.csv
phl_budget_data/data/historical/revenue/wage-collections-by-sector.csv
phl_budget_data/data/historical/spending/actual-department-spending.csv
phl_budget_data/data/historical/spending/budgeted-department-spending-adopted.csv
phl_budget_data/data/historical/spending/budgeted-department-spending-proposed.csv
phl_budget_data/data/historical/spending/budgeted-department-spending.csv
phl_budget_data/qcmr.py
phl_budget_data/revenue.py
phl_budget_data/spending.py
phl_budget_data/utils.py
phl_budget_data-0.2.1.dist-info/entry_points.txt
phl_budget_data-0.2.1.dist-info/LICENSE
phl_budget_data-0.2.1.dist-info/WHEEL
phl_budget_data-0.2.1.dist-info/METADATA
phl_budget_data-0.2.1.dist-info/RECORD
