Metadata-Version: 2.1
Name: phl-budget-data
Version: 0.2.1
Summary: PHL Budget Data
License: MIT
Author: Nick Hand
Author-email: nick.hand@phila.gov
Requires-Python: >=3.8,<4.0
Classifier: License :: OSI Approved :: MIT License
Classifier: Programming Language :: Python :: 3
Classifier: Programming Language :: Python :: 3.10
Classifier: Programming Language :: Python :: 3.8
Classifier: Programming Language :: Python :: 3.9
Requires-Dist: billy-penn (>=0.1.0,<0.2.0)
Requires-Dist: click (==8.0.1)
Requires-Dist: loguru (>=0.5.3,<0.6.0)
Requires-Dist: numpy (>=1.20.1,<2.0.0)
Requires-Dist: openpyxl (>=3.0.7,<4.0.0)
Requires-Dist: pandas (>=1.2.1,<2.0.0)
Requires-Dist: pydantic (>=1.9.0,<2.0.0)
Requires-Dist: rich-click (>=0.3.0,<0.4.0)
